{
  "participantId": "participant_1757826570596_5vzuz87rk",
  "sessionStart": 1757826580318,
  "demographic": {
    "age": "23",
    "education": "Master's degree",
    "profession": "Administrative / Clerical",
    "dataVizBackground": "frequent-user",
    "mediaVisualizationExposure": "Occasionally",
    "visualImpairment": "No",
    "mediaVisualizationHelpfulness": "3",
    "chartFamiliarity": {
      "barCharts": "3",
      "lineCharts": "3",
      "scatterplots": "3",
      "geographicalMaps": "3"
    }
  },
  "responses": [
    {
      "chartId": 6,
      "chartIndex": 1,
      "chartCategory": "Multi-class Scatterplots",
      "understanding": "ddd",
      "factors": "",
      "lasso": [
        {
          "x": 0.8918305597579426,
          "y": 0.2875212585034014
        },
        {
          "x": 0.867624810892587,
          "y": 0.280718537414966
        },
        {
          "x": 0.8040847201210287,
          "y": 0.31246456916099774
        },
        {
          "x": 0.7783661119515886,
          "y": 0.3396754535147392
        },
        {
          "x": 0.7526475037821483,
          "y": 0.3850269274376417
        },
        {
          "x": 0.74357034795764,
          "y": 0.41677295918367346
        },
        {
          "x": 0.7360060514372163,
          "y": 0.5233489229024944
        },
        {
          "x": 0.7465960665658093,
          "y": 0.5823058390022676
        },
        {
          "x": 0.7798789712556732,
          "y": 0.6367276077097506
        },
        {
          "x": 0.8388804841149773,
          "y": 0.6707412131519275
        },
        {
          "x": 0.9099848714069592,
          "y": 0.6662060657596371
        },
        {
          "x": 0.9341906202723147,
          "y": 0.6344600340136054
        },
        {
          "x": 0.9508320726172466,
          "y": 0.5981788548752834
        },
        {
          "x": 0.9674735249621785,
          "y": 0.5324192176870748
        },
        {
          "x": 0.9750378214826021,
          "y": 0.46892715419501135
        },
        {
          "x": 0.9720121028744326,
          "y": 0.4031675170068027
        },
        {
          "x": 0.9568835098335855,
          "y": 0.37142148526077096
        },
        {
          "x": 0.9099848714069592,
          "y": 0.32380243764172334
        },
        {
          "x": 0.8600605143721634,
          "y": 0.31246456916099774
        },
        {
          "x": 0.8918305597579426,
          "y": 0.2875212585034014
        }
      ],
      "lassoSummary": {
        "bbox": {
          "minX": 0.7360060514372163,
          "minY": 0.280718537414966,
          "maxX": 0.9750378214826021,
          "maxY": 0.6707412131519275
        },
        "centroid": {
          "x": 0.8633888048411495,
          "y": 0.45169359410430837
        },
        "area": 0.070980888573281
      },
      "difficultyScale": 3
    },
    {
      "chartId": 39,
      "chartIndex": 2,
      "chartCategory": "Multi-class Maps",
      "understanding": "aa",
      "factors": "",
      "lasso": [
        {
          "x": 0.9145234493192134,
          "y": 0.10611536281179139
        },
        {
          "x": 0.8630862329803328,
          "y": 0.11518565759637188
        },
        {
          "x": 0.8237518910741302,
          "y": 0.1423965419501134
        },
        {
          "x": 0.791981845688351,
          "y": 0.17867772108843538
        },
        {
          "x": 0.7829046898638427,
          "y": 0.21949404761904762
        },
        {
          "x": 0.7904689863842662,
          "y": 0.3283375850340136
        },
        {
          "x": 0.819213313161876,
          "y": 0.40543509070294786
        },
        {
          "x": 0.8736762481089259,
          "y": 0.47799744897959184
        },
        {
          "x": 0.9387291981845688,
          "y": 0.5029407596371882
        },
        {
          "x": 0.9916792738275341,
          "y": 0.4961380385487528
        },
        {
          "x": 0.9901664145234493,
          "y": 0.1809452947845805
        },
        {
          "x": 0.9493192133131618,
          "y": 0.1265235260770975
        },
        {
          "x": 0.9145234493192134,
          "y": 0.10611536281179139
        }
      ],
      "lassoSummary": {
        "bbox": {
          "minX": 0.7829046898638427,
          "minY": 0.10611536281179139,
          "maxX": 0.9916792738275341,
          "maxY": 0.5029407596371882
        },
        "centroid": {
          "x": 0.8803095542883743,
          "y": 0.2604848028955172
        },
        "area": 0.0665280736601247
      },
      "difficultyScale": 3
    },
    {
      "chartId": 23,
      "chartIndex": 3,
      "chartCategory": "Single-class Bar Graphs",
      "understanding": "a",
      "factors": "",
      "lasso": [
        {
          "x": 0.9130105900151286,
          "y": 0.1990858843537415
        },
        {
          "x": 0.8207261724659607,
          "y": 0.26031037414965985
        },
        {
          "x": 0.7723146747352496,
          "y": 0.31473214285714285
        },
        {
          "x": 0.764750378214826,
          "y": 0.35328089569161
        },
        {
          "x": 0.7662632375189108,
          "y": 0.38049178004535145
        },
        {
          "x": 0.7768532526475038,
          "y": 0.42357568027210885
        },
        {
          "x": 0.8040847201210287,
          "y": 0.47119472789115646
        },
        {
          "x": 0.8630862329803328,
          "y": 0.500673185941043
        },
        {
          "x": 0.9462934947049925,
          "y": 0.49840561224489793
        },
        {
          "x": 0.9962178517397882,
          "y": 0.47799744897959184
        },
        {
          "x": 0.9130105900151286,
          "y": 0.1990858843537415
        }
      ],
      "lassoSummary": {
        "bbox": {
          "minX": 0.764750378214826,
          "minY": 0.1990858843537415,
          "maxX": 0.9962178517397882,
          "maxY": 0.500673185941043
        },
        "centroid": {
          "x": 0.8487828359235319,
          "y": 0.3708030560709132
        },
        "area": 0.04579229573826504
      },
      "difficultyScale": 3
    },
    {
      "chartId": 29,
      "chartIndex": 4,
      "chartCategory": "Multi-class Bar Graphs",
      "understanding": "a",
      "factors": "",
      "lasso": [
        {
          "x": 0.6845688350983359,
          "y": 0.117453231292517
        },
        {
          "x": 0.6059001512859304,
          "y": 0.12425595238095238
        },
        {
          "x": 0.5514372163388804,
          "y": 0.14693168934240364
        },
        {
          "x": 0.510590015128593,
          "y": 0.17641014739229025
        },
        {
          "x": 0.4939485627836611,
          "y": 0.1990858843537415
        },
        {
          "x": 0.4803328290468986,
          "y": 0.23763463718820863
        },
        {
          "x": 0.47881996974281393,
          "y": 0.298859126984127
        },
        {
          "x": 0.4863842662632375,
          "y": 0.3283375850340136
        },
        {
          "x": 0.5181543116490166,
          "y": 0.37822420634920634
        },
        {
          "x": 0.575642965204236,
          "y": 0.41677295918367346
        },
        {
          "x": 0.6527987897125568,
          "y": 0.42584325396825395
        },
        {
          "x": 0.699697428139183,
          "y": 0.3963647959183674
        },
        {
          "x": 0.7239031770045385,
          "y": 0.36688633786848074
        },
        {
          "x": 0.754160363086233,
          "y": 0.31019699546485263
        },
        {
          "x": 0.7662632375189108,
          "y": 0.26711309523809523
        },
        {
          "x": 0.7677760968229954,
          "y": 0.21949404761904762
        },
        {
          "x": 0.7511346444780636,
          "y": 0.18548044217687074
        },
        {
          "x": 0.7254160363086233,
          "y": 0.1628047052154195
        },
        {
          "x": 0.705748865355522,
          "y": 0.14919926303854875
        },
        {
          "x": 0.6664145234493192,
          "y": 0.14012896825396826
        },
        {
          "x": 0.6845688350983359,
          "y": 0.117453231292517
        }
      ],
      "lassoSummary": {
        "bbox": {
          "minX": 0.47881996974281393,
          "minY": 0.117453231292517,
          "maxX": 0.7677760968229954,
          "maxY": 0.42584325396825395
        },
        "centroid": {
          "x": 0.6325552914055185,
          "y": 0.24594907407407407
        },
        "area": 0.06730851695191442
      },
      "difficultyScale": 3
    },
    {
      "chartId": 18,
      "chartIndex": 5,
      "chartCategory": "Multi-class Line Charts",
      "understanding": "aa",
      "factors": "",
      "lasso": [
        {
          "x": 0.7859304084720121,
          "y": 0.09704506802721088
        },
        {
          "x": 0.7329803328290468,
          "y": 0.09024234693877552
        },
        {
          "x": 0.7087745839636914,
          "y": 0.09931264172335601
        },
        {
          "x": 0.6724659606656581,
          "y": 0.11972080498866214
        },
        {
          "x": 0.630105900151286,
          "y": 0.16053713151927437
        },
        {
          "x": 0.6180030257186082,
          "y": 0.19681831065759636
        },
        {
          "x": 0.6149773071104387,
          "y": 0.2648455215419501
        },
        {
          "x": 0.6285930408472012,
          "y": 0.335140306122449
        },
        {
          "x": 0.6467473524962178,
          "y": 0.3736890589569161
        },
        {
          "x": 0.6830559757942511,
          "y": 0.4008999433106576
        },
        {
          "x": 0.7254160363086233,
          "y": 0.40543509070294786
        },
        {
          "x": 0.7753403933434191,
          "y": 0.3736890589569161
        },
        {
          "x": 0.8116490166414524,
          "y": 0.33287273242630383
        },
        {
          "x": 0.840393343419062,
          "y": 0.24443735827664398
        },
        {
          "x": 0.846444780635401,
          "y": 0.14693168934240364
        },
        {
          "x": 0.8313161875945537,
          "y": 0.11065051020408163
        },
        {
          "x": 0.74357034795764,
          "y": 0.10384778911564625
        },
        {
          "x": 0.7859304084720121,
          "y": 0.09704506802721088
        }
      ],
      "lassoSummary": {
        "bbox": {
          "minX": 0.6149773071104387,
          "minY": 0.09024234693877552,
          "maxX": 0.846444780635401,
          "maxY": 0.40543509070294786
        },
        "centroid": {
          "x": 0.7267608001344765,
          "y": 0.21962002393550012
        },
        "area": 0.056286256307868626
      },
      "difficultyScale": 3
    },
    {
      "chartId": 1,
      "chartIndex": 6,
      "chartCategory": "Single-class Scatterplots",
      "understanding": "d",
      "factors": "",
      "lasso": [
        {
          "x": 0.7779456193353474,
          "y": 0.17414257369614514
        },
        {
          "x": 0.7658610271903323,
          "y": 0.24670493197278912
        },
        {
          "x": 0.770392749244713,
          "y": 0.33287273242630383
        },
        {
          "x": 0.8006042296072508,
          "y": 0.36915391156462585
        },
        {
          "x": 0.8398791540785498,
          "y": 0.3736890589569161
        },
        {
          "x": 0.8580060422960725,
          "y": 0.3646187641723356
        },
        {
          "x": 0.8716012084592145,
          "y": 0.335140306122449
        },
        {
          "x": 0.879154078549849,
          "y": 0.280718537414966
        },
        {
          "x": 0.7779456193353474,
          "y": 0.17414257369614514
        }
      ],
      "lassoSummary": {
        "bbox": {
          "minX": 0.7658610271903323,
          "minY": 0.17414257369614514,
          "maxX": 0.879154078549849,
          "maxY": 0.3736890589569161
        },
        "centroid": {
          "x": 0.8157099697885196,
          "y": 0.29457593222474177
        },
        "area": 0.014718676997485788
      },
      "difficultyScale": 3
    },
    {
      "chartId": 37,
      "chartIndex": 7,
      "chartCategory": "Multi-class Maps",
      "understanding": "d",
      "factors": "",
      "lasso": [
        {
          "x": 0.729607250755287,
          "y": 0.07890447845804989
        },
        {
          "x": 0.6827794561933535,
          "y": 0.1446641156462585
        },
        {
          "x": 0.6404833836858006,
          "y": 0.23763463718820863
        },
        {
          "x": 0.6238670694864048,
          "y": 0.31473214285714285
        },
        {
          "x": 0.6253776435045317,
          "y": 0.3487457482993197
        },
        {
          "x": 0.6314199395770392,
          "y": 0.36235119047619047
        },
        {
          "x": 0.676737160120846,
          "y": 0.36235119047619047
        },
        {
          "x": 0.7009063444108762,
          "y": 0.3464781746031746
        },
        {
          "x": 0.7462235649546828,
          "y": 0.3011267006802721
        },
        {
          "x": 0.7673716012084593,
          "y": 0.26938066893424034
        },
        {
          "x": 0.7794561933534743,
          "y": 0.208156179138322
        },
        {
          "x": 0.729607250755287,
          "y": 0.07890447845804989
        }
      ],
      "lassoSummary": {
        "bbox": {
          "minX": 0.6238670694864048,
          "minY": 0.07890447845804989,
          "maxX": 0.7794561933534743,
          "maxY": 0.36235119047619047
        },
        "centroid": {
          "x": 0.694486404833837,
          "y": 0.2544524754346183
        },
        "area": 0.026164443622363358
      },
      "difficultyScale": 3
    },
    {
      "chartId": 34,
      "chartIndex": 8,
      "chartCategory": "Single-class Maps",
      "understanding": "d",
      "factors": "",
      "lasso": [
        {
          "x": 0.9003021148036254,
          "y": 0.11518565759637188
        },
        {
          "x": 0.8595166163141994,
          "y": 0.11518565759637188
        },
        {
          "x": 0.8172205438066465,
          "y": 0.12879109977324263
        },
        {
          "x": 0.7205438066465257,
          "y": 0.1809452947845805
        },
        {
          "x": 0.6993957703927492,
          "y": 0.208156179138322
        },
        {
          "x": 0.6827794561933535,
          "y": 0.25350765306122447
        },
        {
          "x": 0.6827794561933535,
          "y": 0.31246456916099774
        },
        {
          "x": 0.6918429003021148,
          "y": 0.3419430272108844
        },
        {
          "x": 0.7129909365558912,
          "y": 0.3736890589569161
        },
        {
          "x": 0.7356495468277946,
          "y": 0.3918296485260771
        },
        {
          "x": 0.8262839879154078,
          "y": 0.3986323696145125
        },
        {
          "x": 0.8867069486404834,
          "y": 0.3850269274376417
        },
        {
          "x": 0.9410876132930514,
          "y": 0.3555484693877551
        },
        {
          "x": 0.9712990936555891,
          "y": 0.3283375850340136
        },
        {
          "x": 0.9984894259818731,
          "y": 0.2829861111111111
        },
        {
          "x": 0.9924471299093656,
          "y": 0.13105867346938777
        },
        {
          "x": 0.8746223564954683,
          "y": 0.08343962585034014
        },
        {
          "x": 0.8293051359516617,
          "y": 0.07663690476190477
        },
        {
          "x": 0.9003021148036254,
          "y": 0.11518565759637188
        }
      ],
      "lassoSummary": {
        "bbox": {
          "minX": 0.6827794561933535,
          "minY": 0.07663690476190477,
          "maxX": 0.9984894259818731,
          "maxY": 0.3986323696145125
        },
        "centroid": {
          "x": 0.8275560502464622,
          "y": 0.2409763247404225
        },
        "area": 0.07399586219180518
      },
      "difficultyScale": 3
    },
    {
      "chartId": 28,
      "chartIndex": 9,
      "chartCategory": "Multi-class Bar Graphs",
      "understanding": "d",
      "factors": "",
      "lasso": [
        {
          "x": 0.9244712990936556,
          "y": 0.26711309523809523
        },
        {
          "x": 0.8942598187311178,
          "y": 0.298859126984127
        },
        {
          "x": 0.8580060422960725,
          "y": 0.36008361678004536
        },
        {
          "x": 0.8323262839879154,
          "y": 0.4394486961451247
        },
        {
          "x": 0.8262839879154078,
          "y": 0.48706774376417233
        },
        {
          "x": 0.8277945619335347,
          "y": 0.5550949546485261
        },
        {
          "x": 0.8459214501510574,
          "y": 0.609516723356009
        },
        {
          "x": 0.8655589123867069,
          "y": 0.6412627551020408
        },
        {
          "x": 0.9033232628398792,
          "y": 0.6548681972789115
        },
        {
          "x": 0.9879154078549849,
          "y": 0.6412627551020408
        },
        {
          "x": 0.9969788519637462,
          "y": 0.30792942176870747
        },
        {
          "x": 0.93202416918429,
          "y": 0.280718537414966
        },
        {
          "x": 0.9244712990936556,
          "y": 0.26711309523809523
        }
      ],
      "lassoSummary": {
        "bbox": {
          "minX": 0.8262839879154078,
          "minY": 0.26711309523809523,
          "maxX": 0.9969788519637462,
          "maxY": 0.6548681972789115
        },
        "centroid": {
          "x": 0.8937950267255401,
          "y": 0.44694913221698934
        },
        "area": 0.05247446410588416
      },
      "difficultyScale": 3
    },
    {
      "chartId": 2,
      "chartIndex": 10,
      "chartCategory": "Single-class Scatterplots",
      "understanding": "d",
      "factors": "",
      "lasso": [
        {
          "x": 0.9395770392749244,
          "y": 0.05169359410430839
        },
        {
          "x": 0.851963746223565,
          "y": 0.16053713151927437
        },
        {
          "x": 0.8413897280966768,
          "y": 0.19681831065759636
        },
        {
          "x": 0.8413897280966768,
          "y": 0.23309948979591838
        },
        {
          "x": 0.851963746223565,
          "y": 0.23990221088435373
        },
        {
          "x": 0.8806646525679759,
          "y": 0.23309948979591838
        },
        {
          "x": 0.9924471299093656,
          "y": 0.153734410430839
        },
        {
          "x": 0.9395770392749244,
          "y": 0.05169359410430839
        }
      ],
      "lassoSummary": {
        "bbox": {
          "minX": 0.8413897280966768,
          "minY": 0.05169359410430839,
          "maxX": 0.9924471299093656,
          "maxY": 0.23990221088435373
        },
        "centroid": {
          "x": 0.8923716012084592,
          "y": 0.16507227891156462
        },
        "area": 0.014292222427742474
      },
      "difficultyScale": 3
    },
    {
      "chartId": 9,
      "chartIndex": 11,
      "chartCategory": "Multi-class Scatterplots",
      "understanding": "d",
      "factors": "",
      "lasso": [
        {
          "x": 0.4788519637462236,
          "y": 0.26711309523809523
        },
        {
          "x": 0.4516616314199396,
          "y": 0.26938066893424034
        },
        {
          "x": 0.4123867069486405,
          "y": 0.29432397959183676
        },
        {
          "x": 0.3610271903323263,
          "y": 0.36235119047619047
        },
        {
          "x": 0.3429003021148036,
          "y": 0.4190405328798186
        },
        {
          "x": 0.33987915407854985,
          "y": 0.4666595804988662
        },
        {
          "x": 0.3459214501510574,
          "y": 0.4916028911564626
        },
        {
          "x": 0.36253776435045315,
          "y": 0.516546201814059
        },
        {
          "x": 0.3957703927492447,
          "y": 0.5301516439909297
        },
        {
          "x": 0.4697885196374622,
          "y": 0.5278840702947846
        },
        {
          "x": 0.5,
          "y": 0.516546201814059
        },
        {
          "x": 0.5589123867069486,
          "y": 0.47799744897959184
        },
        {
          "x": 0.6117824773413897,
          "y": 0.4031675170068027
        },
        {
          "x": 0.622356495468278,
          "y": 0.35328089569161
        },
        {
          "x": 0.620845921450151,
          "y": 0.30566184807256236
        },
        {
          "x": 0.6117824773413897,
          "y": 0.280718537414966
        },
        {
          "x": 0.5800604229607251,
          "y": 0.26031037414965985
        },
        {
          "x": 0.4788519637462236,
          "y": 0.26711309523809523
        }
      ],
      "lassoSummary": {
        "bbox": {
          "minX": 0.33987915407854985,
          "minY": 0.26031037414965985,
          "maxX": 0.622356495468278,
          "maxY": 0.5301516439909297
        },
        "centroid": {
          "x": 0.474739845585767,
          "y": 0.3894360985134794
        },
        "area": 0.05811257030506059
      },
      "difficultyScale": 3
    },
    {
      "chartId": 12,
      "chartIndex": 12,
      "chartCategory": "Single-class Line Charts",
      "understanding": "d",
      "factors": "",
      "lasso": [
        {
          "x": 0.8187311178247734,
          "y": 0.06983418367346939
        },
        {
          "x": 0.8006042296072508,
          "y": 0.06076388888888889
        },
        {
          "x": 0.7537764350453172,
          "y": 0.06756660997732426
        },
        {
          "x": 0.7099697885196374,
          "y": 0.09931264172335601
        },
        {
          "x": 0.676737160120846,
          "y": 0.14693168934240364
        },
        {
          "x": 0.6450151057401813,
          "y": 0.22176162131519275
        },
        {
          "x": 0.6344410876132931,
          "y": 0.2716482426303855
        },
        {
          "x": 0.6299093655589124,
          "y": 0.3396754535147392
        },
        {
          "x": 0.6450151057401813,
          "y": 0.389562074829932
        },
        {
          "x": 0.6737160120845922,
          "y": 0.4008999433106576
        },
        {
          "x": 0.7583081570996979,
          "y": 0.3940972222222222
        },
        {
          "x": 0.8625377643504532,
          "y": 0.35781604308390025
        },
        {
          "x": 0.9123867069486404,
          "y": 0.32153486394557823
        },
        {
          "x": 0.9290030211480362,
          "y": 0.2829861111111111
        },
        {
          "x": 0.93202416918429,
          "y": 0.2353670634920635
        },
        {
          "x": 0.9229607250755287,
          "y": 0.2013534580498866
        },
        {
          "x": 0.9093655589123867,
          "y": 0.17867772108843538
        },
        {
          "x": 0.8867069486404834,
          "y": 0.153734410430839
        },
        {
          "x": 0.8217522658610272,
          "y": 0.11518565759637188
        },
        {
          "x": 0.7764350453172205,
          "y": 0.09024234693877552
        },
        {
          "x": 0.7477341389728097,
          "y": 0.08570719954648526
        },
        {
          "x": 0.8187311178247734,
          "y": 0.06983418367346939
        }
      ],
      "lassoSummary": {
        "bbox": {
          "minX": 0.6299093655589124,
          "minY": 0.06076388888888889,
          "maxX": 0.93202416918429,
          "maxY": 0.4008999433106576
        },
        "centroid": {
          "x": 0.7848118648722877,
          "y": 0.2070223922902494
        },
        "area": 0.07190298072904897
      },
      "difficultyScale": 3
    },
    {
      "chartId": 25,
      "chartIndex": 13,
      "chartCategory": "Single-class Bar Graphs",
      "understanding": "dd",
      "factors": "",
      "lasso": [
        {
          "x": 0.5045317220543807,
          "y": 0.13105867346938777
        },
        {
          "x": 0.4743202416918429,
          "y": 0.11291808390022676
        },
        {
          "x": 0.3987915407854985,
          "y": 0.12198837868480726
        },
        {
          "x": 0.3640483383685801,
          "y": 0.1423965419501134
        },
        {
          "x": 0.324773413897281,
          "y": 0.18321286848072563
        },
        {
          "x": 0.31268882175226587,
          "y": 0.208156179138322
        },
        {
          "x": 0.30513595166163143,
          "y": 0.262577947845805
        },
        {
          "x": 0.30966767371601206,
          "y": 0.31473214285714285
        },
        {
          "x": 0.324773413897281,
          "y": 0.35328089569161
        },
        {
          "x": 0.3504531722054381,
          "y": 0.38049178004535145
        },
        {
          "x": 0.40634441087613293,
          "y": 0.3850269274376417
        },
        {
          "x": 0.4773413897280967,
          "y": 0.36008361678004536
        },
        {
          "x": 0.5347432024169184,
          "y": 0.30566184807256236
        },
        {
          "x": 0.581570996978852,
          "y": 0.21949404761904762
        },
        {
          "x": 0.5906344410876133,
          "y": 0.14012896825396826
        },
        {
          "x": 0.5861027190332326,
          "y": 0.12198837868480726
        },
        {
          "x": 0.5664652567975831,
          "y": 0.10384778911564625
        },
        {
          "x": 0.4818731117824773,
          "y": 0.09931264172335601
        },
        {
          "x": 0.4380664652567976,
          "y": 0.11972080498866214
        },
        {
          "x": 0.42749244712990936,
          "y": 0.14693168934240364
        },
        {
          "x": 0.5045317220543807,
          "y": 0.13105867346938777
        }
      ],
      "lassoSummary": {
        "bbox": {
          "minX": 0.30513595166163143,
          "minY": 0.09931264172335601,
          "maxX": 0.5906344410876133,
          "maxY": 0.3850269274376417
        },
        "centroid": {
          "x": 0.44115954538915264,
          "y": 0.20686042274052482
        },
        "area": 0.06206198491481184
      },
      "difficultyScale": 3
    },
    {
      "chartId": 33,
      "chartIndex": 14,
      "chartCategory": "Single-class Maps",
      "understanding": "dd",
      "factors": "",
      "lasso": [
        {
          "x": 0.6570996978851964,
          "y": 0.18774801587301587
        },
        {
          "x": 0.6057401812688822,
          "y": 0.20362103174603174
        },
        {
          "x": 0.5513595166163142,
          "y": 0.25124007936507936
        },
        {
          "x": 0.5151057401812689,
          "y": 0.3011267006802721
        },
        {
          "x": 0.49697885196374625,
          "y": 0.36235119047619047
        },
        {
          "x": 0.49395770392749244,
          "y": 0.3986323696145125
        },
        {
          "x": 0.5060422960725075,
          "y": 0.4916028911564626
        },
        {
          "x": 0.5438066465256798,
          "y": 0.5664328231292517
        },
        {
          "x": 0.5649546827794562,
          "y": 0.5913761337868481
        },
        {
          "x": 0.648036253776435,
          "y": 0.6457979024943311
        },
        {
          "x": 0.7401812688821753,
          "y": 0.6639384920634921
        },
        {
          "x": 0.7779456193353474,
          "y": 0.6639384920634921
        },
        {
          "x": 0.8141993957703928,
          "y": 0.6480654761904762
        },
        {
          "x": 0.851963746223565,
          "y": 0.5959112811791383
        },
        {
          "x": 0.8806646525679759,
          "y": 0.5278840702947846
        },
        {
          "x": 0.8912386706948641,
          "y": 0.47346230158730157
        },
        {
          "x": 0.8912386706948641,
          "y": 0.41223781179138325
        },
        {
          "x": 0.8836858006042296,
          "y": 0.3827593537414966
        },
        {
          "x": 0.8700906344410876,
          "y": 0.35328089569161
        },
        {
          "x": 0.8383685800604229,
          "y": 0.31699971655328796
        },
        {
          "x": 0.7401812688821753,
          "y": 0.24443735827664398
        },
        {
          "x": 0.6450151057401813,
          "y": 0.20588860544217688
        },
        {
          "x": 0.6102719033232629,
          "y": 0.208156179138322
        },
        {
          "x": 0.5996978851963746,
          "y": 0.22402919501133786
        },
        {
          "x": 0.6570996978851964,
          "y": 0.18774801587301587
        }
      ],
      "lassoSummary": {
        "bbox": {
          "minX": 0.49395770392749244,
          "minY": 0.18774801587301587,
          "maxX": 0.8912386706948641,
          "maxY": 0.6639384920634921
        },
        "centroid": {
          "x": 0.6909969788519638,
          "y": 0.4043466553287982
        },
        "area": 0.13822094799651988
      },
      "difficultyScale": 3
    },
    {
      "chartId": 20,
      "chartIndex": 15,
      "chartCategory": "Multi-class Line Charts",
      "understanding": "dd",
      "factors": "",
      "lasso": [
        {
          "x": 0.7779456193353474,
          "y": 0.1628047052154195
        },
        {
          "x": 0.675226586102719,
          "y": 0.18321286848072563
        },
        {
          "x": 0.5785498489425982,
          "y": 0.23309948979591838
        },
        {
          "x": 0.5498489425981873,
          "y": 0.280718537414966
        },
        {
          "x": 0.5453172205438066,
          "y": 0.3306051587301587
        },
        {
          "x": 0.5513595166163142,
          "y": 0.3646187641723356
        },
        {
          "x": 0.5619335347432024,
          "y": 0.3827593537414966
        },
        {
          "x": 0.5785498489425982,
          "y": 0.3918296485260771
        },
        {
          "x": 0.6102719033232629,
          "y": 0.3918296485260771
        },
        {
          "x": 0.6827794561933535,
          "y": 0.37822420634920634
        },
        {
          "x": 0.7265861027190332,
          "y": 0.3555484693877551
        },
        {
          "x": 0.7628398791540786,
          "y": 0.31246456916099774
        },
        {
          "x": 0.7870090634441088,
          "y": 0.25577522675736963
        },
        {
          "x": 0.797583081570997,
          "y": 0.18321286848072563
        },
        {
          "x": 0.7824773413897281,
          "y": 0.18321286848072563
        },
        {
          "x": 0.7779456193353474,
          "y": 0.1628047052154195
        }
      ],
      "lassoSummary": {
        "bbox": {
          "minX": 0.5453172205438066,
          "minY": 0.1628047052154195,
          "maxX": 0.797583081570997,
          "maxY": 0.3918296485260771
        },
        "centroid": {
          "x": 0.6716389728096677,
          "y": 0.2845450680272109
        },
        "area": 0.0399976707702215
      },
      "difficultyScale": 3
    },
    {
      "chartId": 14,
      "chartIndex": 16,
      "chartCategory": "Single-class Line Charts",
      "understanding": "dd",
      "factors": "",
      "lasso": [
        {
          "x": 0.6963746223564955,
          "y": 0.21269132653061223
        },
        {
          "x": 0.648036253776435,
          "y": 0.2285643424036281
        },
        {
          "x": 0.5936555891238671,
          "y": 0.26938066893424034
        },
        {
          "x": 0.5589123867069486,
          "y": 0.30339427437641725
        },
        {
          "x": 0.5226586102719033,
          "y": 0.36235119047619047
        },
        {
          "x": 0.5120845921450151,
          "y": 0.40543509070294786
        },
        {
          "x": 0.5181268882175226,
          "y": 0.48933531746031744
        },
        {
          "x": 0.5483383685800605,
          "y": 0.5664328231292517
        },
        {
          "x": 0.5725075528700906,
          "y": 0.5913761337868481
        },
        {
          "x": 0.6057401812688822,
          "y": 0.6049815759637188
        },
        {
          "x": 0.6450151057401813,
          "y": 0.607249149659864
        },
        {
          "x": 0.7039274924471299,
          "y": 0.5936437074829932
        },
        {
          "x": 0.7583081570996979,
          "y": 0.5664328231292517
        },
        {
          "x": 0.8081570996978852,
          "y": 0.5233489229024944
        },
        {
          "x": 0.8716012084592145,
          "y": 0.40543509070294786
        },
        {
          "x": 0.877643504531722,
          "y": 0.32153486394557823
        },
        {
          "x": 0.8398791540785498,
          "y": 0.2784509637188209
        },
        {
          "x": 0.7250755287009063,
          "y": 0.23083191609977324
        },
        {
          "x": 0.6586102719033232,
          "y": 0.22402919501133786
        },
        {
          "x": 0.6374622356495468,
          "y": 0.23763463718820863
        },
        {
          "x": 0.6963746223564955,
          "y": 0.21269132653061223
        }
      ],
      "lassoSummary": {
        "bbox": {
          "minX": 0.5120845921450151,
          "minY": 0.21269132653061223,
          "maxX": 0.877643504531722,
          "maxY": 0.607249149659864
        },
        "centroid": {
          "x": 0.6665947345705654,
          "y": 0.3921535876255263
        },
        "area": 0.10448822026292894
      },
      "difficultyScale": 3
    }
  ],
  "sessionId": "TEY7gaH3In2SlHuXLZfSFudnI0A-Cr4H",
  "selectedCharts": [
    6,
    39,
    23,
    29,
    18,
    1,
    37,
    34,
    28,
    2,
    9,
    12,
    25,
    33,
    20,
    14
  ],
  "chartCategories": {
    "1": "Single-class Scatterplots",
    "2": "Single-class Scatterplots",
    "6": "Multi-class Scatterplots",
    "9": "Multi-class Scatterplots",
    "12": "Single-class Line Charts",
    "14": "Single-class Line Charts",
    "18": "Multi-class Line Charts",
    "20": "Multi-class Line Charts",
    "23": "Single-class Bar Graphs",
    "25": "Single-class Bar Graphs",
    "28": "Multi-class Bar Graphs",
    "29": "Multi-class Bar Graphs",
    "33": "Single-class Maps",
    "34": "Single-class Maps",
    "37": "Multi-class Maps",
    "39": "Multi-class Maps"
  },
  "mainStudyCompletedAt": "2025-09-14T05:12:06.860Z",
  "totalTimeMinutes": 2,
  "mainStudyCompletionTime": 1757826726860,
  "studyTiming": {
    "startTime": 1757826592841,
    "endTime": 1757826726860,
    "totalDurationMs": 134019,
    "totalDurationSeconds": 134,
    "totalDurationMinutes": 2,
    "formattedDuration": "2:14"
  },
  "postStudy": {
    "recognizedCharts": [
      39,
      37
    ],
    "feedback": "bfccf",
    "completedAt": "2025-09-14T05:12:18.253Z"
  },
  "studyCompleteTimestamp": 1757826738253,
  "timestamp": 1757826738259,
  "studyStartTime": 1757826570596,
  "studyDuration": 167663,
  "vlTestSelfReportedScore": {
    "overallScore": 4,
    "maxScore": 12,
    "percentage": 33
  },
  "dataQualityFlags": {
    "suspiciousText": false,
    "gibberishResponses": false,
    "tooShortResponses": true,
    "rapidCompletion": false
  }
}